falcon_confiante/__init__.py
falcon_confiante/middleware.py
falcon_confiante/router.py
falcon_confiante-0.2.7.dist-info/DESCRIPTION.rst
falcon_confiante-0.2.7.dist-info/METADATA
falcon_confiante-0.2.7.dist-info/RECORD
falcon_confiante-0.2.7.dist-info/WHEEL
falcon_confiante-0.2.7.dist-info/metadata.json
falcon_confiante-0.2.7.dist-info/top_level.txt
