Metadata-Version: 2.0
Name: falcon-confiante
Version: 0.2.7
Summary: Custom router an middleware to Spec Driven Development using OpenAPI v3 and Falcon.
Home-page: https://github.com/ecarrara/falcon-confiante
Author: Erle Carrara
Author-email: carrara.erle@gmail.com
License: UNKNOWN
Keywords: falcon,openapi,api,swagger
Platform: UNKNOWN
Classifier: Programming Language :: Python :: 3
Classifier: License :: OSI Approved :: MIT License
Classifier: Operating System :: OS Independent
Requires-Python: >=2.7, !=3.0.*, !=3.1.*, !=3.2.*, !=3.3.*
Requires-Dist: jsonschema (>=2.6.0)
Requires-Dist: falcon (<2.0.0,>=1.4.0)
